mplgrid/__about__.py
mplgrid/__init__.py
mplgrid/mplgrid.py
mplgrid-0.3.0.dist-info/METADATA
mplgrid-0.3.0.dist-info/WHEEL
mplgrid-0.3.0.dist-info/licenses/LICENSE
mplgrid-0.3.0.dist-info/RECORD
